{
  "predictions": [
    {
      "x": 571.5,
      "y": 326.0,
      "width": 39.0,
      "height": 88.0,
      "confidence": 0.8122460246086121,
      "class": "plants",
      "class_id": 0,
      "detection_id": "d6b65690-6c82-4daf-8cca-44dcb86b240e",
      "image_path": "C:/Own/University/\u0414\u0413\u0422\u0423/\u0412\u041c\u041e/6 \u0441\u0435\u043c\u0435\u0441\u0442\u0440/\u041f\u0440\u043e\u0438\u0437\u0432\u043e\u0434\u0441\u0442\u0432\u0435\u043d\u043d\u0430\u044f \u043f\u0440\u0430\u043a\u0442\u0438\u043a\u0430/\u041f\u0440\u043e\u0435\u043a\u0442/dataset/images/Rostselmash-1/whole/images/240521_gopro11_gx010066_01767.jpg",
      "prediction_type": "ObjectDetectionModel"
    },
    {
      "x": 173.0,
      "y": 576.5,
      "width": 38.0,
      "height": 61.0,
      "confidence": 0.8108210563659668,
      "class": "plants",
      "class_id": 0,
      "detection_id": "be48c840-f90d-41bb-97d5-ed6bf0a88450",
      "image_path": "C:/Own/University/\u0414\u0413\u0422\u0423/\u0412\u041c\u041e/6 \u0441\u0435\u043c\u0435\u0441\u0442\u0440/\u041f\u0440\u043e\u0438\u0437\u0432\u043e\u0434\u0441\u0442\u0432\u0435\u043d\u043d\u0430\u044f \u043f\u0440\u0430\u043a\u0442\u0438\u043a\u0430/\u041f\u0440\u043e\u0435\u043a\u0442/dataset/images/Rostselmash-1/whole/images/240521_gopro11_gx010066_01767.jpg",
      "prediction_type": "ObjectDetectionModel"
    },
    {
      "x": 183.5,
      "y": 308.0,
      "width": 35.0,
      "height": 46.0,
      "confidence": 0.8046512603759766,
      "class": "plants",
      "class_id": 0,
      "detection_id": "041d45fb-c70a-45f6-a59f-d341d2763a76",
      "image_path": "C:/Own/University/\u0414\u0413\u0422\u0423/\u0412\u041c\u041e/6 \u0441\u0435\u043c\u0435\u0441\u0442\u0440/\u041f\u0440\u043e\u0438\u0437\u0432\u043e\u0434\u0441\u0442\u0432\u0435\u043d\u043d\u0430\u044f \u043f\u0440\u0430\u043a\u0442\u0438\u043a\u0430/\u041f\u0440\u043e\u0435\u043a\u0442/dataset/images/Rostselmash-1/whole/images/240521_gopro11_gx010066_01767.jpg",
      "prediction_type": "ObjectDetectionModel"
    },
    {
      "x": 267.5,
      "y": 610.0,
      "width": 41.0,
      "height": 60.0,
      "confidence": 0.8005189895629883,
      "class": "plants",
      "class_id": 0,
      "detection_id": "e76042f0-d70e-4762-967c-8a311c1ef909",
      "image_path": "C:/Own/University/\u0414\u0413\u0422\u0423/\u0412\u041c\u041e/6 \u0441\u0435\u043c\u0435\u0441\u0442\u0440/\u041f\u0440\u043e\u0438\u0437\u0432\u043e\u0434\u0441\u0442\u0432\u0435\u043d\u043d\u0430\u044f \u043f\u0440\u0430\u043a\u0442\u0438\u043a\u0430/\u041f\u0440\u043e\u0435\u043a\u0442/dataset/images/Rostselmash-1/whole/images/240521_gopro11_gx010066_01767.jpg",
      "prediction_type": "ObjectDetectionModel"
    },
    {
      "x": 529.0,
      "y": 158.0,
      "width": 38.0,
      "height": 60.0,
      "confidence": 0.7742273807525635,
      "class": "plants",
      "class_id": 0,
      "detection_id": "76eae083-7d81-4771-872c-afaa3de09fe6",
      "image_path": "C:/Own/University/\u0414\u0413\u0422\u0423/\u0412\u041c\u041e/6 \u0441\u0435\u043c\u0435\u0441\u0442\u0440/\u041f\u0440\u043e\u0438\u0437\u0432\u043e\u0434\u0441\u0442\u0432\u0435\u043d\u043d\u0430\u044f \u043f\u0440\u0430\u043a\u0442\u0438\u043a\u0430/\u041f\u0440\u043e\u0435\u043a\u0442/dataset/images/Rostselmash-1/whole/images/240521_gopro11_gx010066_01767.jpg",
      "prediction_type": "ObjectDetectionModel"
    },
    {
      "x": 23.0,
      "y": 342.5,
      "width": 38.0,
      "height": 73.0,
      "confidence": 0.7693836688995361,
      "class": "plants",
      "class_id": 0,
      "detection_id": "b782ab6b-ddd8-4d53-a6a5-8ed7021bc41f",
      "image_path": "C:/Own/University/\u0414\u0413\u0422\u0423/\u0412\u041c\u041e/6 \u0441\u0435\u043c\u0435\u0441\u0442\u0440/\u041f\u0440\u043e\u0438\u0437\u0432\u043e\u0434\u0441\u0442\u0432\u0435\u043d\u043d\u0430\u044f \u043f\u0440\u0430\u043a\u0442\u0438\u043a\u0430/\u041f\u0440\u043e\u0435\u043a\u0442/dataset/images/Rostselmash-1/whole/images/240521_gopro11_gx010066_01767.jpg",
      "prediction_type": "ObjectDetectionModel"
    },
    {
      "x": 314.5,
      "y": 55.5,
      "width": 39.0,
      "height": 83.0,
      "confidence": 0.7227833867073059,
      "class": "plants",
      "class_id": 0,
      "detection_id": "5dca18db-6671-4ed1-a737-be2d37cf7f30",
      "image_path": "C:/Own/University/\u0414\u0413\u0422\u0423/\u0412\u041c\u041e/6 \u0441\u0435\u043c\u0435\u0441\u0442\u0440/\u041f\u0440\u043e\u0438\u0437\u0432\u043e\u0434\u0441\u0442\u0432\u0435\u043d\u043d\u0430\u044f \u043f\u0440\u0430\u043a\u0442\u0438\u043a\u0430/\u041f\u0440\u043e\u0435\u043a\u0442/dataset/images/Rostselmash-1/whole/images/240521_gopro11_gx010066_01767.jpg",
      "prediction_type": "ObjectDetectionModel"
    },
    {
      "x": 203.5,
      "y": 106.5,
      "width": 29.0,
      "height": 35.0,
      "confidence": 0.7097910046577454,
      "class": "plants",
      "class_id": 0,
      "detection_id": "46cb750a-78f3-4db3-b33b-da442b32d6b7",
      "image_path": "C:/Own/University/\u0414\u0413\u0422\u0423/\u0412\u041c\u041e/6 \u0441\u0435\u043c\u0435\u0441\u0442\u0440/\u041f\u0440\u043e\u0438\u0437\u0432\u043e\u0434\u0441\u0442\u0432\u0435\u043d\u043d\u0430\u044f \u043f\u0440\u0430\u043a\u0442\u0438\u043a\u0430/\u041f\u0440\u043e\u0435\u043a\u0442/dataset/images/Rostselmash-1/whole/images/240521_gopro11_gx010066_01767.jpg",
      "prediction_type": "ObjectDetectionModel"
    },
    {
      "x": 14.0,
      "y": 278.5,
      "width": 28.0,
      "height": 45.0,
      "confidence": 0.7067623138427734,
      "class": "plants",
      "class_id": 0,
      "detection_id": "6259c3b7-4c8e-4ddd-b973-c43a45e6ea83",
      "image_path": "C:/Own/University/\u0414\u0413\u0422\u0423/\u0412\u041c\u041e/6 \u0441\u0435\u043c\u0435\u0441\u0442\u0440/\u041f\u0440\u043e\u0438\u0437\u0432\u043e\u0434\u0441\u0442\u0432\u0435\u043d\u043d\u0430\u044f \u043f\u0440\u0430\u043a\u0442\u0438\u043a\u0430/\u041f\u0440\u043e\u0435\u043a\u0442/dataset/images/Rostselmash-1/whole/images/240521_gopro11_gx010066_01767.jpg",
      "prediction_type": "ObjectDetectionModel"
    },
    {
      "x": 408.0,
      "y": 415.5,
      "width": 36.0,
      "height": 87.0,
      "confidence": 0.6877684593200684,
      "class": "plants",
      "class_id": 0,
      "detection_id": "1bf255b5-a350-4c95-bb00-e355eb05f46b",
      "image_path": "C:/Own/University/\u0414\u0413\u0422\u0423/\u0412\u041c\u041e/6 \u0441\u0435\u043c\u0435\u0441\u0442\u0440/\u041f\u0440\u043e\u0438\u0437\u0432\u043e\u0434\u0441\u0442\u0432\u0435\u043d\u043d\u0430\u044f \u043f\u0440\u0430\u043a\u0442\u0438\u043a\u0430/\u041f\u0440\u043e\u0435\u043a\u0442/dataset/images/Rostselmash-1/whole/images/240521_gopro11_gx010066_01767.jpg",
      "prediction_type": "ObjectDetectionModel"
    },
    {
      "x": 544.5,
      "y": 217.5,
      "width": 29.0,
      "height": 41.0,
      "confidence": 0.6862903237342834,
      "class": "plants",
      "class_id": 0,
      "detection_id": "a3be28e9-3948-4b46-bf5f-2e283071c821",
      "image_path": "C:/Own/University/\u0414\u0413\u0422\u0423/\u0412\u041c\u041e/6 \u0441\u0435\u043c\u0435\u0441\u0442\u0440/\u041f\u0440\u043e\u0438\u0437\u0432\u043e\u0434\u0441\u0442\u0432\u0435\u043d\u043d\u0430\u044f \u043f\u0440\u0430\u043a\u0442\u0438\u043a\u0430/\u041f\u0440\u043e\u0435\u043a\u0442/dataset/images/Rostselmash-1/whole/images/240521_gopro11_gx010066_01767.jpg",
      "prediction_type": "ObjectDetectionModel"
    },
    {
      "x": 45.5,
      "y": 432.5,
      "width": 49.0,
      "height": 69.0,
      "confidence": 0.6732949614524841,
      "class": "plants",
      "class_id": 0,
      "detection_id": "cce730cc-8a04-49ca-bd2f-449cbe6c76a5",
      "image_path": "C:/Own/University/\u0414\u0413\u0422\u0423/\u0412\u041c\u041e/6 \u0441\u0435\u043c\u0435\u0441\u0442\u0440/\u041f\u0440\u043e\u0438\u0437\u0432\u043e\u0434\u0441\u0442\u0432\u0435\u043d\u043d\u0430\u044f \u043f\u0440\u0430\u043a\u0442\u0438\u043a\u0430/\u041f\u0440\u043e\u0435\u043a\u0442/dataset/images/Rostselmash-1/whole/images/240521_gopro11_gx010066_01767.jpg",
      "prediction_type": "ObjectDetectionModel"
    },
    {
      "x": 462.5,
      "y": 14.5,
      "width": 33.0,
      "height": 29.0,
      "confidence": 0.6680481433868408,
      "class": "plants",
      "class_id": 0,
      "detection_id": "f0d2ac2e-c129-4a11-9a2e-344e880f2cc9",
      "image_path": "C:/Own/University/\u0414\u0413\u0422\u0423/\u0412\u041c\u041e/6 \u0441\u0435\u043c\u0435\u0441\u0442\u0440/\u041f\u0440\u043e\u0438\u0437\u0432\u043e\u0434\u0441\u0442\u0432\u0435\u043d\u043d\u0430\u044f \u043f\u0440\u0430\u043a\u0442\u0438\u043a\u0430/\u041f\u0440\u043e\u0435\u043a\u0442/dataset/images/Rostselmash-1/whole/images/240521_gopro11_gx010066_01767.jpg",
      "prediction_type": "ObjectDetectionModel"
    },
    {
      "x": 603.5,
      "y": 561.5,
      "width": 31.0,
      "height": 35.0,
      "confidence": 0.6621169447898865,
      "class": "plants",
      "class_id": 0,
      "detection_id": "72aaff07-8572-4578-b58d-35067f23dcb3",
      "image_path": "C:/Own/University/\u0414\u0413\u0422\u0423/\u0412\u041c\u041e/6 \u0441\u0435\u043c\u0435\u0441\u0442\u0440/\u041f\u0440\u043e\u0438\u0437\u0432\u043e\u0434\u0441\u0442\u0432\u0435\u043d\u043d\u0430\u044f \u043f\u0440\u0430\u043a\u0442\u0438\u043a\u0430/\u041f\u0440\u043e\u0435\u043a\u0442/dataset/images/Rostselmash-1/whole/images/240521_gopro11_gx010066_01767.jpg",
      "prediction_type": "ObjectDetectionModel"
    },
    {
      "x": 368.0,
      "y": 119.0,
      "width": 34.0,
      "height": 38.0,
      "confidence": 0.6557458639144897,
      "class": "plants",
      "class_id": 0,
      "detection_id": "f4a52858-d7bf-460f-b215-6dc58ea2ee12",
      "image_path": "C:/Own/University/\u0414\u0413\u0422\u0423/\u0412\u041c\u041e/6 \u0441\u0435\u043c\u0435\u0441\u0442\u0440/\u041f\u0440\u043e\u0438\u0437\u0432\u043e\u0434\u0441\u0442\u0432\u0435\u043d\u043d\u0430\u044f \u043f\u0440\u0430\u043a\u0442\u0438\u043a\u0430/\u041f\u0440\u043e\u0435\u043a\u0442/dataset/images/Rostselmash-1/whole/images/240521_gopro11_gx010066_01767.jpg",
      "prediction_type": "ObjectDetectionModel"
    },
    {
      "x": 159.5,
      "y": 479.0,
      "width": 29.0,
      "height": 40.0,
      "confidence": 0.6398332118988037,
      "class": "plants",
      "class_id": 0,
      "detection_id": "0f9eba50-a59d-450d-acab-1f6fe7045490",
      "image_path": "C:/Own/University/\u0414\u0413\u0422\u0423/\u0412\u041c\u041e/6 \u0441\u0435\u043c\u0435\u0441\u0442\u0440/\u041f\u0440\u043e\u0438\u0437\u0432\u043e\u0434\u0441\u0442\u0432\u0435\u043d\u043d\u0430\u044f \u043f\u0440\u0430\u043a\u0442\u0438\u043a\u0430/\u041f\u0440\u043e\u0435\u043a\u0442/dataset/images/Rostselmash-1/whole/images/240521_gopro11_gx010066_01767.jpg",
      "prediction_type": "ObjectDetectionModel"
    },
    {
      "x": 496.5,
      "y": 90.5,
      "width": 31.0,
      "height": 33.0,
      "confidence": 0.635520339012146,
      "class": "plants",
      "class_id": 0,
      "detection_id": "71de3abc-719e-42fb-9041-52129d814616",
      "image_path": "C:/Own/University/\u0414\u0413\u0422\u0423/\u0412\u041c\u041e/6 \u0441\u0435\u043c\u0435\u0441\u0442\u0440/\u041f\u0440\u043e\u0438\u0437\u0432\u043e\u0434\u0441\u0442\u0432\u0435\u043d\u043d\u0430\u044f \u043f\u0440\u0430\u043a\u0442\u0438\u043a\u0430/\u041f\u0440\u043e\u0435\u043a\u0442/dataset/images/Rostselmash-1/whole/images/240521_gopro11_gx010066_01767.jpg",
      "prediction_type": "ObjectDetectionModel"
    },
    {
      "x": 127.5,
      "y": 18.0,
      "width": 37.0,
      "height": 36.0,
      "confidence": 0.6300464868545532,
      "class": "plants",
      "class_id": 0,
      "detection_id": "6b0c2c85-33bf-4e42-9a00-781b0113e64e",
      "image_path": "C:/Own/University/\u0414\u0413\u0422\u0423/\u0412\u041c\u041e/6 \u0441\u0435\u043c\u0435\u0441\u0442\u0440/\u041f\u0440\u043e\u0438\u0437\u0432\u043e\u0434\u0441\u0442\u0432\u0435\u043d\u043d\u0430\u044f \u043f\u0440\u0430\u043a\u0442\u0438\u043a\u0430/\u041f\u0440\u043e\u0435\u043a\u0442/dataset/images/Rostselmash-1/whole/images/240521_gopro11_gx010066_01767.jpg",
      "prediction_type": "ObjectDetectionModel"
    },
    {
      "x": 353.0,
      "y": 185.0,
      "width": 26.0,
      "height": 46.0,
      "confidence": 0.6289001703262329,
      "class": "plants",
      "class_id": 0,
      "detection_id": "2905b770-d708-43de-883f-33910b1f5ab8",
      "image_path": "C:/Own/University/\u0414\u0413\u0422\u0423/\u0412\u041c\u041e/6 \u0441\u0435\u043c\u0435\u0441\u0442\u0440/\u041f\u0440\u043e\u0438\u0437\u0432\u043e\u0434\u0441\u0442\u0432\u0435\u043d\u043d\u0430\u044f \u043f\u0440\u0430\u043a\u0442\u0438\u043a\u0430/\u041f\u0440\u043e\u0435\u043a\u0442/dataset/images/Rostselmash-1/whole/images/240521_gopro11_gx010066_01767.jpg",
      "prediction_type": "ObjectDetectionModel"
    },
    {
      "x": 13.5,
      "y": 228.5,
      "width": 25.0,
      "height": 41.0,
      "confidence": 0.627439022064209,
      "class": "plants",
      "class_id": 0,
      "detection_id": "a6cf5aa9-1493-4d77-9e4d-5e2435722db6",
      "image_path": "C:/Own/University/\u0414\u0413\u0422\u0423/\u0412\u041c\u041e/6 \u0441\u0435\u043c\u0435\u0441\u0442\u0440/\u041f\u0440\u043e\u0438\u0437\u0432\u043e\u0434\u0441\u0442\u0432\u0435\u043d\u043d\u0430\u044f \u043f\u0440\u0430\u043a\u0442\u0438\u043a\u0430/\u041f\u0440\u043e\u0435\u043a\u0442/dataset/images/Rostselmash-1/whole/images/240521_gopro11_gx010066_01767.jpg",
      "prediction_type": "ObjectDetectionModel"
    },
    {
      "x": 87.5,
      "y": 296.0,
      "width": 23.0,
      "height": 38.0,
      "confidence": 0.6268429756164551,
      "class": "plants",
      "class_id": 0,
      "detection_id": "9b5b94bf-d686-4143-940f-468986a318e0",
      "image_path": "C:/Own/University/\u0414\u0413\u0422\u0423/\u0412\u041c\u041e/6 \u0441\u0435\u043c\u0435\u0441\u0442\u0440/\u041f\u0440\u043e\u0438\u0437\u0432\u043e\u0434\u0441\u0442\u0432\u0435\u043d\u043d\u0430\u044f \u043f\u0440\u0430\u043a\u0442\u0438\u043a\u0430/\u041f\u0440\u043e\u0435\u043a\u0442/dataset/images/Rostselmash-1/whole/images/240521_gopro11_gx010066_01767.jpg",
      "prediction_type": "ObjectDetectionModel"
    },
    {
      "x": 596.0,
      "y": 614.0,
      "width": 26.0,
      "height": 50.0,
      "confidence": 0.6216064691543579,
      "class": "plants",
      "class_id": 0,
      "detection_id": "19e189a3-98b8-4e4d-b10c-dc71a9d5113f",
      "image_path": "C:/Own/University/\u0414\u0413\u0422\u0423/\u0412\u041c\u041e/6 \u0441\u0435\u043c\u0435\u0441\u0442\u0440/\u041f\u0440\u043e\u0438\u0437\u0432\u043e\u0434\u0441\u0442\u0432\u0435\u043d\u043d\u0430\u044f \u043f\u0440\u0430\u043a\u0442\u0438\u043a\u0430/\u041f\u0440\u043e\u0435\u043a\u0442/dataset/images/Rostselmash-1/whole/images/240521_gopro11_gx010066_01767.jpg",
      "prediction_type": "ObjectDetectionModel"
    },
    {
      "x": 119.0,
      "y": 602.5,
      "width": 26.0,
      "height": 41.0,
      "confidence": 0.6068201065063477,
      "class": "plants",
      "class_id": 0,
      "detection_id": "454761d6-9bb4-4d15-b509-2b01fe0e1cd4",
      "image_path": "C:/Own/University/\u0414\u0413\u0422\u0423/\u0412\u041c\u041e/6 \u0441\u0435\u043c\u0435\u0441\u0442\u0440/\u041f\u0440\u043e\u0438\u0437\u0432\u043e\u0434\u0441\u0442\u0432\u0435\u043d\u043d\u0430\u044f \u043f\u0440\u0430\u043a\u0442\u0438\u043a\u0430/\u041f\u0440\u043e\u0435\u043a\u0442/dataset/images/Rostselmash-1/whole/images/240521_gopro11_gx010066_01767.jpg",
      "prediction_type": "ObjectDetectionModel"
    },
    {
      "x": 17.0,
      "y": 615.0,
      "width": 34.0,
      "height": 50.0,
      "confidence": 0.6032348871231079,
      "class": "plants",
      "class_id": 0,
      "detection_id": "2359279a-63d1-4552-abfe-9028306f04ce",
      "image_path": "C:/Own/University/\u0414\u0413\u0422\u0423/\u0412\u041c\u041e/6 \u0441\u0435\u043c\u0435\u0441\u0442\u0440/\u041f\u0440\u043e\u0438\u0437\u0432\u043e\u0434\u0441\u0442\u0432\u0435\u043d\u043d\u0430\u044f \u043f\u0440\u0430\u043a\u0442\u0438\u043a\u0430/\u041f\u0440\u043e\u0435\u043a\u0442/dataset/images/Rostselmash-1/whole/images/240521_gopro11_gx010066_01767.jpg",
      "prediction_type": "ObjectDetectionModel"
    },
    {
      "x": 439.0,
      "y": 592.0,
      "width": 28.0,
      "height": 54.0,
      "confidence": 0.6031323671340942,
      "class": "plants",
      "class_id": 0,
      "detection_id": "2d477365-3120-4909-8176-2437bfd0db16",
      "image_path": "C:/Own/University/\u0414\u0413\u0422\u0423/\u0412\u041c\u041e/6 \u0441\u0435\u043c\u0435\u0441\u0442\u0440/\u041f\u0440\u043e\u0438\u0437\u0432\u043e\u0434\u0441\u0442\u0432\u0435\u043d\u043d\u0430\u044f \u043f\u0440\u0430\u043a\u0442\u0438\u043a\u0430/\u041f\u0440\u043e\u0435\u043a\u0442/dataset/images/Rostselmash-1/whole/images/240521_gopro11_gx010066_01767.jpg",
      "prediction_type": "ObjectDetectionModel"
    },
    {
      "x": 140.5,
      "y": 110.0,
      "width": 41.0,
      "height": 58.0,
      "confidence": 0.5940083265304565,
      "class": "plants",
      "class_id": 0,
      "detection_id": "4f3fc8df-af4f-4bda-8b39-81609344696f",
      "image_path": "C:/Own/University/\u0414\u0413\u0422\u0423/\u0412\u041c\u041e/6 \u0441\u0435\u043c\u0435\u0441\u0442\u0440/\u041f\u0440\u043e\u0438\u0437\u0432\u043e\u0434\u0441\u0442\u0432\u0435\u043d\u043d\u0430\u044f \u043f\u0440\u0430\u043a\u0442\u0438\u043a\u0430/\u041f\u0440\u043e\u0435\u043a\u0442/dataset/images/Rostselmash-1/whole/images/240521_gopro11_gx010066_01767.jpg",
      "prediction_type": "ObjectDetectionModel"
    },
    {
      "x": 481.5,
      "y": 50.5,
      "width": 33.0,
      "height": 43.0,
      "confidence": 0.591568648815155,
      "class": "plants",
      "class_id": 0,
      "detection_id": "568cf186-3f33-4553-9826-4337199633ab",
      "image_path": "C:/Own/University/\u0414\u0413\u0422\u0423/\u0412\u041c\u041e/6 \u0441\u0435\u043c\u0435\u0441\u0442\u0440/\u041f\u0440\u043e\u0438\u0437\u0432\u043e\u0434\u0441\u0442\u0432\u0435\u043d\u043d\u0430\u044f \u043f\u0440\u0430\u043a\u0442\u0438\u043a\u0430/\u041f\u0440\u043e\u0435\u043a\u0442/dataset/images/Rostselmash-1/whole/images/240521_gopro11_gx010066_01767.jpg",
      "prediction_type": "ObjectDetectionModel"
    },
    {
      "x": 250.0,
      "y": 552.5,
      "width": 26.0,
      "height": 49.0,
      "confidence": 0.5829366445541382,
      "class": "plants",
      "class_id": 0,
      "detection_id": "0c5201f1-d030-483a-ae0b-82eda54ba22e",
      "image_path": "C:/Own/University/\u0414\u0413\u0422\u0423/\u0412\u041c\u041e/6 \u0441\u0435\u043c\u0435\u0441\u0442\u0440/\u041f\u0440\u043e\u0438\u0437\u0432\u043e\u0434\u0441\u0442\u0432\u0435\u043d\u043d\u0430\u044f \u043f\u0440\u0430\u043a\u0442\u0438\u043a\u0430/\u041f\u0440\u043e\u0435\u043a\u0442/dataset/images/Rostselmash-1/whole/images/240521_gopro11_gx010066_01767.jpg",
      "prediction_type": "ObjectDetectionModel"
    },
    {
      "x": 172.5,
      "y": 259.0,
      "width": 21.0,
      "height": 40.0,
      "confidence": 0.5813920497894287,
      "class": "plants",
      "class_id": 0,
      "detection_id": "beef7af9-6b1b-4cc5-aab1-19e27affae1b",
      "image_path": "C:/Own/University/\u0414\u0413\u0422\u0423/\u0412\u041c\u041e/6 \u0441\u0435\u043c\u0435\u0441\u0442\u0440/\u041f\u0440\u043e\u0438\u0437\u0432\u043e\u0434\u0441\u0442\u0432\u0435\u043d\u043d\u0430\u044f \u043f\u0440\u0430\u043a\u0442\u0438\u043a\u0430/\u041f\u0440\u043e\u0435\u043a\u0442/dataset/images/Rostselmash-1/whole/images/240521_gopro11_gx010066_01767.jpg",
      "prediction_type": "ObjectDetectionModel"
    },
    {
      "x": 481.5,
      "y": 589.0,
      "width": 23.0,
      "height": 38.0,
      "confidence": 0.5517116785049438,
      "class": "plants",
      "class_id": 0,
      "detection_id": "723083a0-4cfd-4b18-a4d3-4160d237c499",
      "image_path": "C:/Own/University/\u0414\u0413\u0422\u0423/\u0412\u041c\u041e/6 \u0441\u0435\u043c\u0435\u0441\u0442\u0440/\u041f\u0440\u043e\u0438\u0437\u0432\u043e\u0434\u0441\u0442\u0432\u0435\u043d\u043d\u0430\u044f \u043f\u0440\u0430\u043a\u0442\u0438\u043a\u0430/\u041f\u0440\u043e\u0435\u043a\u0442/dataset/images/Rostselmash-1/whole/images/240521_gopro11_gx010066_01767.jpg",
      "prediction_type": "ObjectDetectionModel"
    },
    {
      "x": 270.0,
      "y": 127.0,
      "width": 28.0,
      "height": 48.0,
      "confidence": 0.551408052444458,
      "class": "plants",
      "class_id": 0,
      "detection_id": "6beef715-f28e-4d2c-aeac-82100f48b572",
      "image_path": "C:/Own/University/\u0414\u0413\u0422\u0423/\u0412\u041c\u041e/6 \u0441\u0435\u043c\u0435\u0441\u0442\u0440/\u041f\u0440\u043e\u0438\u0437\u0432\u043e\u0434\u0441\u0442\u0432\u0435\u043d\u043d\u0430\u044f \u043f\u0440\u0430\u043a\u0442\u0438\u043a\u0430/\u041f\u0440\u043e\u0435\u043a\u0442/dataset/images/Rostselmash-1/whole/images/240521_gopro11_gx010066_01767.jpg",
      "prediction_type": "ObjectDetectionModel"
    },
    {
      "x": 221.5,
      "y": 448.5,
      "width": 45.0,
      "height": 65.0,
      "confidence": 0.5454844236373901,
      "class": "plants",
      "class_id": 0,
      "detection_id": "34483665-e09f-4924-acdc-bb495884afde",
      "image_path": "C:/Own/University/\u0414\u0413\u0422\u0423/\u0412\u041c\u041e/6 \u0441\u0435\u043c\u0435\u0441\u0442\u0440/\u041f\u0440\u043e\u0438\u0437\u0432\u043e\u0434\u0441\u0442\u0432\u0435\u043d\u043d\u0430\u044f \u043f\u0440\u0430\u043a\u0442\u0438\u043a\u0430/\u041f\u0440\u043e\u0435\u043a\u0442/dataset/images/Rostselmash-1/whole/images/240521_gopro11_gx010066_01767.jpg",
      "prediction_type": "ObjectDetectionModel"
    },
    {
      "x": 213.5,
      "y": 391.5,
      "width": 53.0,
      "height": 47.0,
      "confidence": 0.544599175453186,
      "class": "plants",
      "class_id": 0,
      "detection_id": "f2f0feaf-722e-46f4-a080-ccf76bc2a67a",
      "image_path": "C:/Own/University/\u0414\u0413\u0422\u0423/\u0412\u041c\u041e/6 \u0441\u0435\u043c\u0435\u0441\u0442\u0440/\u041f\u0440\u043e\u0438\u0437\u0432\u043e\u0434\u0441\u0442\u0432\u0435\u043d\u043d\u0430\u044f \u043f\u0440\u0430\u043a\u0442\u0438\u043a\u0430/\u041f\u0440\u043e\u0435\u043a\u0442/dataset/images/Rostselmash-1/whole/images/240521_gopro11_gx010066_01767.jpg",
      "prediction_type": "ObjectDetectionModel"
    },
    {
      "x": 503.0,
      "y": 126.0,
      "width": 20.0,
      "height": 32.0,
      "confidence": 0.5339488387107849,
      "class": "plants",
      "class_id": 0,
      "detection_id": "209f3ae1-4768-44bb-a64c-47e9eb0096fc",
      "image_path": "C:/Own/University/\u0414\u0413\u0422\u0423/\u0412\u041c\u041e/6 \u0441\u0435\u043c\u0435\u0441\u0442\u0440/\u041f\u0440\u043e\u0438\u0437\u0432\u043e\u0434\u0441\u0442\u0432\u0435\u043d\u043d\u0430\u044f \u043f\u0440\u0430\u043a\u0442\u0438\u043a\u0430/\u041f\u0440\u043e\u0435\u043a\u0442/dataset/images/Rostselmash-1/whole/images/240521_gopro11_gx010066_01767.jpg",
      "prediction_type": "ObjectDetectionModel"
    },
    {
      "x": 227.5,
      "y": 593.5,
      "width": 17.0,
      "height": 29.0,
      "confidence": 0.5297092199325562,
      "class": "plants",
      "class_id": 0,
      "detection_id": "0240f5af-c288-479b-99ec-89b380f27ac4",
      "image_path": "C:/Own/University/\u0414\u0413\u0422\u0423/\u0412\u041c\u041e/6 \u0441\u0435\u043c\u0435\u0441\u0442\u0440/\u041f\u0440\u043e\u0438\u0437\u0432\u043e\u0434\u0441\u0442\u0432\u0435\u043d\u043d\u0430\u044f \u043f\u0440\u0430\u043a\u0442\u0438\u043a\u0430/\u041f\u0440\u043e\u0435\u043a\u0442/dataset/images/Rostselmash-1/whole/images/240521_gopro11_gx010066_01767.jpg",
      "prediction_type": "ObjectDetectionModel"
    },
    {
      "x": 552.0,
      "y": 262.0,
      "width": 20.0,
      "height": 30.0,
      "confidence": 0.5268971920013428,
      "class": "plants",
      "class_id": 0,
      "detection_id": "9953cd23-a715-405d-ae37-a6cc47cd9902",
      "image_path": "C:/Own/University/\u0414\u0413\u0422\u0423/\u0412\u041c\u041e/6 \u0441\u0435\u043c\u0435\u0441\u0442\u0440/\u041f\u0440\u043e\u0438\u0437\u0432\u043e\u0434\u0441\u0442\u0432\u0435\u043d\u043d\u0430\u044f \u043f\u0440\u0430\u043a\u0442\u0438\u043a\u0430/\u041f\u0440\u043e\u0435\u043a\u0442/dataset/images/Rostselmash-1/whole/images/240521_gopro11_gx010066_01767.jpg",
      "prediction_type": "ObjectDetectionModel"
    },
    {
      "x": 242.5,
      "y": 208.0,
      "width": 31.0,
      "height": 62.0,
      "confidence": 0.5214363932609558,
      "class": "plants",
      "class_id": 0,
      "detection_id": "c3ef2f01-7763-453f-9fca-490ff4117d71",
      "image_path": "C:/Own/University/\u0414\u0413\u0422\u0423/\u0412\u041c\u041e/6 \u0441\u0435\u043c\u0435\u0441\u0442\u0440/\u041f\u0440\u043e\u0438\u0437\u0432\u043e\u0434\u0441\u0442\u0432\u0435\u043d\u043d\u0430\u044f \u043f\u0440\u0430\u043a\u0442\u0438\u043a\u0430/\u041f\u0440\u043e\u0435\u043a\u0442/dataset/images/Rostselmash-1/whole/images/240521_gopro11_gx010066_01767.jpg",
      "prediction_type": "ObjectDetectionModel"
    }
  ],
  "image": {
    "width": "640",
    "height": "640"
  }
}