{
  "predictions": [
    {
      "x": 246.0,
      "y": 469.0,
      "width": 90.0,
      "height": 54.0,
      "confidence": 0.9132497906684875,
      "class": "plants",
      "class_id": 0,
      "detection_id": "d30b24f5-43df-4b13-bf57-a175c1c933cc",
      "image_path": "C:/Own/University/\u0414\u0413\u0422\u0423/\u0412\u041c\u041e/6 \u0441\u0435\u043c\u0435\u0441\u0442\u0440/\u041f\u0440\u043e\u0438\u0437\u0432\u043e\u0434\u0441\u0442\u0432\u0435\u043d\u043d\u0430\u044f \u043f\u0440\u0430\u043a\u0442\u0438\u043a\u0430/\u041f\u0440\u043e\u0435\u043a\u0442/dataset/images/Rostselmash-1/whole/images/240521_gopro9_gx020424_00483.jpg",
      "prediction_type": "ObjectDetectionModel"
    },
    {
      "x": 184.5,
      "y": 592.0,
      "width": 71.0,
      "height": 48.0,
      "confidence": 0.8967549800872803,
      "class": "plants",
      "class_id": 0,
      "detection_id": "376ce91b-262b-40d6-9b99-2c5bce7486b6",
      "image_path": "C:/Own/University/\u0414\u0413\u0422\u0423/\u0412\u041c\u041e/6 \u0441\u0435\u043c\u0435\u0441\u0442\u0440/\u041f\u0440\u043e\u0438\u0437\u0432\u043e\u0434\u0441\u0442\u0432\u0435\u043d\u043d\u0430\u044f \u043f\u0440\u0430\u043a\u0442\u0438\u043a\u0430/\u041f\u0440\u043e\u0435\u043a\u0442/dataset/images/Rostselmash-1/whole/images/240521_gopro9_gx020424_00483.jpg",
      "prediction_type": "ObjectDetectionModel"
    },
    {
      "x": 462.0,
      "y": 547.0,
      "width": 54.0,
      "height": 44.0,
      "confidence": 0.8574508428573608,
      "class": "plants",
      "class_id": 0,
      "detection_id": "367141d3-a5ec-45bd-87b9-2e76b63eea9b",
      "image_path": "C:/Own/University/\u0414\u0413\u0422\u0423/\u0412\u041c\u041e/6 \u0441\u0435\u043c\u0435\u0441\u0442\u0440/\u041f\u0440\u043e\u0438\u0437\u0432\u043e\u0434\u0441\u0442\u0432\u0435\u043d\u043d\u0430\u044f \u043f\u0440\u0430\u043a\u0442\u0438\u043a\u0430/\u041f\u0440\u043e\u0435\u043a\u0442/dataset/images/Rostselmash-1/whole/images/240521_gopro9_gx020424_00483.jpg",
      "prediction_type": "ObjectDetectionModel"
    },
    {
      "x": 274.0,
      "y": 595.0,
      "width": 58.0,
      "height": 32.0,
      "confidence": 0.8461303114891052,
      "class": "plants",
      "class_id": 0,
      "detection_id": "2281b7d7-b4bd-4c56-9e5e-9b66e4c3bc8e",
      "image_path": "C:/Own/University/\u0414\u0413\u0422\u0423/\u0412\u041c\u041e/6 \u0441\u0435\u043c\u0435\u0441\u0442\u0440/\u041f\u0440\u043e\u0438\u0437\u0432\u043e\u0434\u0441\u0442\u0432\u0435\u043d\u043d\u0430\u044f \u043f\u0440\u0430\u043a\u0442\u0438\u043a\u0430/\u041f\u0440\u043e\u0435\u043a\u0442/dataset/images/Rostselmash-1/whole/images/240521_gopro9_gx020424_00483.jpg",
      "prediction_type": "ObjectDetectionModel"
    },
    {
      "x": 286.0,
      "y": 347.5,
      "width": 68.0,
      "height": 39.0,
      "confidence": 0.8372248411178589,
      "class": "plants",
      "class_id": 0,
      "detection_id": "4b924ae9-bf28-4eaf-bcc4-16ec60473def",
      "image_path": "C:/Own/University/\u0414\u0413\u0422\u0423/\u0412\u041c\u041e/6 \u0441\u0435\u043c\u0435\u0441\u0442\u0440/\u041f\u0440\u043e\u0438\u0437\u0432\u043e\u0434\u0441\u0442\u0432\u0435\u043d\u043d\u0430\u044f \u043f\u0440\u0430\u043a\u0442\u0438\u043a\u0430/\u041f\u0440\u043e\u0435\u043a\u0442/dataset/images/Rostselmash-1/whole/images/240521_gopro9_gx020424_00483.jpg",
      "prediction_type": "ObjectDetectionModel"
    },
    {
      "x": 220.5,
      "y": 528.5,
      "width": 55.0,
      "height": 37.0,
      "confidence": 0.8314419984817505,
      "class": "plants",
      "class_id": 0,
      "detection_id": "1879fe0b-5acf-4be9-ba8a-582697f15407",
      "image_path": "C:/Own/University/\u0414\u0413\u0422\u0423/\u0412\u041c\u041e/6 \u0441\u0435\u043c\u0435\u0441\u0442\u0440/\u041f\u0440\u043e\u0438\u0437\u0432\u043e\u0434\u0441\u0442\u0432\u0435\u043d\u043d\u0430\u044f \u043f\u0440\u0430\u043a\u0442\u0438\u043a\u0430/\u041f\u0440\u043e\u0435\u043a\u0442/dataset/images/Rostselmash-1/whole/images/240521_gopro9_gx020424_00483.jpg",
      "prediction_type": "ObjectDetectionModel"
    },
    {
      "x": 222.0,
      "y": 345.0,
      "width": 60.0,
      "height": 32.0,
      "confidence": 0.8228762149810791,
      "class": "plants",
      "class_id": 0,
      "detection_id": "f8a07e16-72e2-4986-8e1b-657acd56871e",
      "image_path": "C:/Own/University/\u0414\u0413\u0422\u0423/\u0412\u041c\u041e/6 \u0441\u0435\u043c\u0435\u0441\u0442\u0440/\u041f\u0440\u043e\u0438\u0437\u0432\u043e\u0434\u0441\u0442\u0432\u0435\u043d\u043d\u0430\u044f \u043f\u0440\u0430\u043a\u0442\u0438\u043a\u0430/\u041f\u0440\u043e\u0435\u043a\u0442/dataset/images/Rostselmash-1/whole/images/240521_gopro9_gx020424_00483.jpg",
      "prediction_type": "ObjectDetectionModel"
    },
    {
      "x": 164.0,
      "y": 524.5,
      "width": 70.0,
      "height": 41.0,
      "confidence": 0.8207870125770569,
      "class": "plants",
      "class_id": 0,
      "detection_id": "a48e112c-a010-4cd1-b7c0-547c9306ab72",
      "image_path": "C:/Own/University/\u0414\u0413\u0422\u0423/\u0412\u041c\u041e/6 \u0441\u0435\u043c\u0435\u0441\u0442\u0440/\u041f\u0440\u043e\u0438\u0437\u0432\u043e\u0434\u0441\u0442\u0432\u0435\u043d\u043d\u0430\u044f \u043f\u0440\u0430\u043a\u0442\u0438\u043a\u0430/\u041f\u0440\u043e\u0435\u043a\u0442/dataset/images/Rostselmash-1/whole/images/240521_gopro9_gx020424_00483.jpg",
      "prediction_type": "ObjectDetectionModel"
    },
    {
      "x": 411.0,
      "y": 336.0,
      "width": 56.0,
      "height": 34.0,
      "confidence": 0.8193230032920837,
      "class": "plants",
      "class_id": 0,
      "detection_id": "ffd8af74-9634-41fc-9f25-4bbc92bd96d2",
      "image_path": "C:/Own/University/\u0414\u0413\u0422\u0423/\u0412\u041c\u041e/6 \u0441\u0435\u043c\u0435\u0441\u0442\u0440/\u041f\u0440\u043e\u0438\u0437\u0432\u043e\u0434\u0441\u0442\u0432\u0435\u043d\u043d\u0430\u044f \u043f\u0440\u0430\u043a\u0442\u0438\u043a\u0430/\u041f\u0440\u043e\u0435\u043a\u0442/dataset/images/Rostselmash-1/whole/images/240521_gopro9_gx020424_00483.jpg",
      "prediction_type": "ObjectDetectionModel"
    },
    {
      "x": 71.0,
      "y": 577.0,
      "width": 48.0,
      "height": 30.0,
      "confidence": 0.8135979175567627,
      "class": "plants",
      "class_id": 0,
      "detection_id": "e749e292-f6f0-4d38-aa66-3bc2986007cd",
      "image_path": "C:/Own/University/\u0414\u0413\u0422\u0423/\u0412\u041c\u041e/6 \u0441\u0435\u043c\u0435\u0441\u0442\u0440/\u041f\u0440\u043e\u0438\u0437\u0432\u043e\u0434\u0441\u0442\u0432\u0435\u043d\u043d\u0430\u044f \u043f\u0440\u0430\u043a\u0442\u0438\u043a\u0430/\u041f\u0440\u043e\u0435\u043a\u0442/dataset/images/Rostselmash-1/whole/images/240521_gopro9_gx020424_00483.jpg",
      "prediction_type": "ObjectDetectionModel"
    },
    {
      "x": 530.0,
      "y": 523.5,
      "width": 56.0,
      "height": 37.0,
      "confidence": 0.7922194600105286,
      "class": "plants",
      "class_id": 0,
      "detection_id": "87c047a9-0338-4a37-830e-2a75729ce80f",
      "image_path": "C:/Own/University/\u0414\u0413\u0422\u0423/\u0412\u041c\u041e/6 \u0441\u0435\u043c\u0435\u0441\u0442\u0440/\u041f\u0440\u043e\u0438\u0437\u0432\u043e\u0434\u0441\u0442\u0432\u0435\u043d\u043d\u0430\u044f \u043f\u0440\u0430\u043a\u0442\u0438\u043a\u0430/\u041f\u0440\u043e\u0435\u043a\u0442/dataset/images/Rostselmash-1/whole/images/240521_gopro9_gx020424_00483.jpg",
      "prediction_type": "ObjectDetectionModel"
    },
    {
      "x": 477.0,
      "y": 332.5,
      "width": 60.0,
      "height": 33.0,
      "confidence": 0.7903044819831848,
      "class": "plants",
      "class_id": 0,
      "detection_id": "83a55f0e-bbaf-468b-baaa-b2de3b584c45",
      "image_path": "C:/Own/University/\u0414\u0413\u0422\u0423/\u0412\u041c\u041e/6 \u0441\u0435\u043c\u0435\u0441\u0442\u0440/\u041f\u0440\u043e\u0438\u0437\u0432\u043e\u0434\u0441\u0442\u0432\u0435\u043d\u043d\u0430\u044f \u043f\u0440\u0430\u043a\u0442\u0438\u043a\u0430/\u041f\u0440\u043e\u0435\u043a\u0442/dataset/images/Rostselmash-1/whole/images/240521_gopro9_gx020424_00483.jpg",
      "prediction_type": "ObjectDetectionModel"
    },
    {
      "x": 352.0,
      "y": 545.0,
      "width": 48.0,
      "height": 28.0,
      "confidence": 0.7743958830833435,
      "class": "plants",
      "class_id": 0,
      "detection_id": "9c569fba-d653-449c-b851-70db9d7446a1",
      "image_path": "C:/Own/University/\u0414\u0413\u0422\u0423/\u0412\u041c\u041e/6 \u0441\u0435\u043c\u0435\u0441\u0442\u0440/\u041f\u0440\u043e\u0438\u0437\u0432\u043e\u0434\u0441\u0442\u0432\u0435\u043d\u043d\u0430\u044f \u043f\u0440\u0430\u043a\u0442\u0438\u043a\u0430/\u041f\u0440\u043e\u0435\u043a\u0442/dataset/images/Rostselmash-1/whole/images/240521_gopro9_gx020424_00483.jpg",
      "prediction_type": "ObjectDetectionModel"
    },
    {
      "x": 20.5,
      "y": 354.0,
      "width": 41.0,
      "height": 30.0,
      "confidence": 0.7669360637664795,
      "class": "plants",
      "class_id": 0,
      "detection_id": "416ed457-f026-4a55-a2b6-db864b0fe75e",
      "image_path": "C:/Own/University/\u0414\u0413\u0422\u0423/\u0412\u041c\u041e/6 \u0441\u0435\u043c\u0435\u0441\u0442\u0440/\u041f\u0440\u043e\u0438\u0437\u0432\u043e\u0434\u0441\u0442\u0432\u0435\u043d\u043d\u0430\u044f \u043f\u0440\u0430\u043a\u0442\u0438\u043a\u0430/\u041f\u0440\u043e\u0435\u043a\u0442/dataset/images/Rostselmash-1/whole/images/240521_gopro9_gx020424_00483.jpg",
      "prediction_type": "ObjectDetectionModel"
    },
    {
      "x": 440.5,
      "y": 74.5,
      "width": 39.0,
      "height": 25.0,
      "confidence": 0.7553930282592773,
      "class": "plants",
      "class_id": 0,
      "detection_id": "2e8a68ac-b76a-41fd-9011-4e9715686d43",
      "image_path": "C:/Own/University/\u0414\u0413\u0422\u0423/\u0412\u041c\u041e/6 \u0441\u0435\u043c\u0435\u0441\u0442\u0440/\u041f\u0440\u043e\u0438\u0437\u0432\u043e\u0434\u0441\u0442\u0432\u0435\u043d\u043d\u0430\u044f \u043f\u0440\u0430\u043a\u0442\u0438\u043a\u0430/\u041f\u0440\u043e\u0435\u043a\u0442/dataset/images/Rostselmash-1/whole/images/240521_gopro9_gx020424_00483.jpg",
      "prediction_type": "ObjectDetectionModel"
    },
    {
      "x": 94.5,
      "y": 68.0,
      "width": 35.0,
      "height": 24.0,
      "confidence": 0.7468897104263306,
      "class": "plants",
      "class_id": 0,
      "detection_id": "568836af-95a8-4e82-bf3e-c0c3268e3892",
      "image_path": "C:/Own/University/\u0414\u0413\u0422\u0423/\u0412\u041c\u041e/6 \u0441\u0435\u043c\u0435\u0441\u0442\u0440/\u041f\u0440\u043e\u0438\u0437\u0432\u043e\u0434\u0441\u0442\u0432\u0435\u043d\u043d\u0430\u044f \u043f\u0440\u0430\u043a\u0442\u0438\u043a\u0430/\u041f\u0440\u043e\u0435\u043a\u0442/dataset/images/Rostselmash-1/whole/images/240521_gopro9_gx020424_00483.jpg",
      "prediction_type": "ObjectDetectionModel"
    },
    {
      "x": 317.5,
      "y": 62.0,
      "width": 49.0,
      "height": 26.0,
      "confidence": 0.721248984336853,
      "class": "plants",
      "class_id": 0,
      "detection_id": "017e5160-0ffe-4c79-a6f9-54fd5fc158a0",
      "image_path": "C:/Own/University/\u0414\u0413\u0422\u0423/\u0412\u041c\u041e/6 \u0441\u0435\u043c\u0435\u0441\u0442\u0440/\u041f\u0440\u043e\u0438\u0437\u0432\u043e\u0434\u0441\u0442\u0432\u0435\u043d\u043d\u0430\u044f \u043f\u0440\u0430\u043a\u0442\u0438\u043a\u0430/\u041f\u0440\u043e\u0435\u043a\u0442/dataset/images/Rostselmash-1/whole/images/240521_gopro9_gx020424_00483.jpg",
      "prediction_type": "ObjectDetectionModel"
    },
    {
      "x": 365.0,
      "y": 67.0,
      "width": 46.0,
      "height": 22.0,
      "confidence": 0.7090269923210144,
      "class": "plants",
      "class_id": 0,
      "detection_id": "c0190f79-c232-4088-a3e6-bcd73b62fba2",
      "image_path": "C:/Own/University/\u0414\u0413\u0422\u0423/\u0412\u041c\u041e/6 \u0441\u0435\u043c\u0435\u0441\u0442\u0440/\u041f\u0440\u043e\u0438\u0437\u0432\u043e\u0434\u0441\u0442\u0432\u0435\u043d\u043d\u0430\u044f \u043f\u0440\u0430\u043a\u0442\u0438\u043a\u0430/\u041f\u0440\u043e\u0435\u043a\u0442/dataset/images/Rostselmash-1/whole/images/240521_gopro9_gx020424_00483.jpg",
      "prediction_type": "ObjectDetectionModel"
    },
    {
      "x": 337.5,
      "y": 513.0,
      "width": 51.0,
      "height": 28.0,
      "confidence": 0.7044262886047363,
      "class": "plants",
      "class_id": 0,
      "detection_id": "48b034bc-eae2-41bc-a841-c16c68cc114c",
      "image_path": "C:/Own/University/\u0414\u0413\u0422\u0423/\u0412\u041c\u041e/6 \u0441\u0435\u043c\u0435\u0441\u0442\u0440/\u041f\u0440\u043e\u0438\u0437\u0432\u043e\u0434\u0441\u0442\u0432\u0435\u043d\u043d\u0430\u044f \u043f\u0440\u0430\u043a\u0442\u0438\u043a\u0430/\u041f\u0440\u043e\u0435\u043a\u0442/dataset/images/Rostselmash-1/whole/images/240521_gopro9_gx020424_00483.jpg",
      "prediction_type": "ObjectDetectionModel"
    },
    {
      "x": 514.0,
      "y": 12.0,
      "width": 34.0,
      "height": 20.0,
      "confidence": 0.7000603675842285,
      "class": "plants",
      "class_id": 0,
      "detection_id": "4b250dd7-4f3c-466a-87e9-9545082d318b",
      "image_path": "C:/Own/University/\u0414\u0413\u0422\u0423/\u0412\u041c\u041e/6 \u0441\u0435\u043c\u0435\u0441\u0442\u0440/\u041f\u0440\u043e\u0438\u0437\u0432\u043e\u0434\u0441\u0442\u0432\u0435\u043d\u043d\u0430\u044f \u043f\u0440\u0430\u043a\u0442\u0438\u043a\u0430/\u041f\u0440\u043e\u0435\u043a\u0442/dataset/images/Rostselmash-1/whole/images/240521_gopro9_gx020424_00483.jpg",
      "prediction_type": "ObjectDetectionModel"
    },
    {
      "x": 132.5,
      "y": 66.0,
      "width": 37.0,
      "height": 22.0,
      "confidence": 0.6877273321151733,
      "class": "plants",
      "class_id": 0,
      "detection_id": "4e50de57-fbfb-47ac-90c6-32312f8d55d9",
      "image_path": "C:/Own/University/\u0414\u0413\u0422\u0423/\u0412\u041c\u041e/6 \u0441\u0435\u043c\u0435\u0441\u0442\u0440/\u041f\u0440\u043e\u0438\u0437\u0432\u043e\u0434\u0441\u0442\u0432\u0435\u043d\u043d\u0430\u044f \u043f\u0440\u0430\u043a\u0442\u0438\u043a\u0430/\u041f\u0440\u043e\u0435\u043a\u0442/dataset/images/Rostselmash-1/whole/images/240521_gopro9_gx020424_00483.jpg",
      "prediction_type": "ObjectDetectionModel"
    },
    {
      "x": 147.5,
      "y": 184.0,
      "width": 35.0,
      "height": 30.0,
      "confidence": 0.6822649240493774,
      "class": "plants",
      "class_id": 0,
      "detection_id": "d4d01d3e-12a3-43fa-ba42-1b57b857148c",
      "image_path": "C:/Own/University/\u0414\u0413\u0422\u0423/\u0412\u041c\u041e/6 \u0441\u0435\u043c\u0435\u0441\u0442\u0440/\u041f\u0440\u043e\u0438\u0437\u0432\u043e\u0434\u0441\u0442\u0432\u0435\u043d\u043d\u0430\u044f \u043f\u0440\u0430\u043a\u0442\u0438\u043a\u0430/\u041f\u0440\u043e\u0435\u043a\u0442/dataset/images/Rostselmash-1/whole/images/240521_gopro9_gx020424_00483.jpg",
      "prediction_type": "ObjectDetectionModel"
    },
    {
      "x": 64.5,
      "y": 461.0,
      "width": 35.0,
      "height": 20.0,
      "confidence": 0.6744405031204224,
      "class": "plants",
      "class_id": 0,
      "detection_id": "ecca046f-f321-4c9a-bc8d-346826581234",
      "image_path": "C:/Own/University/\u0414\u0413\u0422\u0423/\u0412\u041c\u041e/6 \u0441\u0435\u043c\u0435\u0441\u0442\u0440/\u041f\u0440\u043e\u0438\u0437\u0432\u043e\u0434\u0441\u0442\u0432\u0435\u043d\u043d\u0430\u044f \u043f\u0440\u0430\u043a\u0442\u0438\u043a\u0430/\u041f\u0440\u043e\u0435\u043a\u0442/dataset/images/Rostselmash-1/whole/images/240521_gopro9_gx020424_00483.jpg",
      "prediction_type": "ObjectDetectionModel"
    },
    {
      "x": 548.5,
      "y": 22.5,
      "width": 35.0,
      "height": 21.0,
      "confidence": 0.6703132390975952,
      "class": "plants",
      "class_id": 0,
      "detection_id": "2e690689-79b1-4ad5-99a3-7213b317f0a2",
      "image_path": "C:/Own/University/\u0414\u0413\u0422\u0423/\u0412\u041c\u041e/6 \u0441\u0435\u043c\u0435\u0441\u0442\u0440/\u041f\u0440\u043e\u0438\u0437\u0432\u043e\u0434\u0441\u0442\u0432\u0435\u043d\u043d\u0430\u044f \u043f\u0440\u0430\u043a\u0442\u0438\u043a\u0430/\u041f\u0440\u043e\u0435\u043a\u0442/dataset/images/Rostselmash-1/whole/images/240521_gopro9_gx020424_00483.jpg",
      "prediction_type": "ObjectDetectionModel"
    },
    {
      "x": 317.0,
      "y": 186.5,
      "width": 36.0,
      "height": 21.0,
      "confidence": 0.6689587831497192,
      "class": "plants",
      "class_id": 0,
      "detection_id": "37681f6c-6a6a-4609-b399-4e2bf2baa025",
      "image_path": "C:/Own/University/\u0414\u0413\u0422\u0423/\u0412\u041c\u041e/6 \u0441\u0435\u043c\u0435\u0441\u0442\u0440/\u041f\u0440\u043e\u0438\u0437\u0432\u043e\u0434\u0441\u0442\u0432\u0435\u043d\u043d\u0430\u044f \u043f\u0440\u0430\u043a\u0442\u0438\u043a\u0430/\u041f\u0440\u043e\u0435\u043a\u0442/dataset/images/Rostselmash-1/whole/images/240521_gopro9_gx020424_00483.jpg",
      "prediction_type": "ObjectDetectionModel"
    },
    {
      "x": 449.5,
      "y": 493.5,
      "width": 39.0,
      "height": 23.0,
      "confidence": 0.6658457517623901,
      "class": "plants",
      "class_id": 0,
      "detection_id": "bc6b3074-6283-4382-9e47-ac8d835175f6",
      "image_path": "C:/Own/University/\u0414\u0413\u0422\u0423/\u0412\u041c\u041e/6 \u0441\u0435\u043c\u0435\u0441\u0442\u0440/\u041f\u0440\u043e\u0438\u0437\u0432\u043e\u0434\u0441\u0442\u0432\u0435\u043d\u043d\u0430\u044f \u043f\u0440\u0430\u043a\u0442\u0438\u043a\u0430/\u041f\u0440\u043e\u0435\u043a\u0442/dataset/images/Rostselmash-1/whole/images/240521_gopro9_gx020424_00483.jpg",
      "prediction_type": "ObjectDetectionModel"
    },
    {
      "x": 403.0,
      "y": 71.5,
      "width": 32.0,
      "height": 19.0,
      "confidence": 0.6514779329299927,
      "class": "plants",
      "class_id": 0,
      "detection_id": "6ce74c5c-38d0-4444-bf0d-2b21a6e577f0",
      "image_path": "C:/Own/University/\u0414\u0413\u0422\u0423/\u0412\u041c\u041e/6 \u0441\u0435\u043c\u0435\u0441\u0442\u0440/\u041f\u0440\u043e\u0438\u0437\u0432\u043e\u0434\u0441\u0442\u0432\u0435\u043d\u043d\u0430\u044f \u043f\u0440\u0430\u043a\u0442\u0438\u043a\u0430/\u041f\u0440\u043e\u0435\u043a\u0442/dataset/images/Rostselmash-1/whole/images/240521_gopro9_gx020424_00483.jpg",
      "prediction_type": "ObjectDetectionModel"
    },
    {
      "x": 545.0,
      "y": 285.0,
      "width": 32.0,
      "height": 18.0,
      "confidence": 0.6508957743644714,
      "class": "plants",
      "class_id": 0,
      "detection_id": "a28a1db5-8fb8-4f32-ac48-2d17e459694a",
      "image_path": "C:/Own/University/\u0414\u0413\u0422\u0423/\u0412\u041c\u041e/6 \u0441\u0435\u043c\u0435\u0441\u0442\u0440/\u041f\u0440\u043e\u0438\u0437\u0432\u043e\u0434\u0441\u0442\u0432\u0435\u043d\u043d\u0430\u044f \u043f\u0440\u0430\u043a\u0442\u0438\u043a\u0430/\u041f\u0440\u043e\u0435\u043a\u0442/dataset/images/Rostselmash-1/whole/images/240521_gopro9_gx020424_00483.jpg",
      "prediction_type": "ObjectDetectionModel"
    },
    {
      "x": 258.0,
      "y": 632.0,
      "width": 42.0,
      "height": 16.0,
      "confidence": 0.6391799449920654,
      "class": "plants",
      "class_id": 0,
      "detection_id": "048568ee-0746-4fa0-8ab1-2e5b6e11d0ff",
      "image_path": "C:/Own/University/\u0414\u0413\u0422\u0423/\u0412\u041c\u041e/6 \u0441\u0435\u043c\u0435\u0441\u0442\u0440/\u041f\u0440\u043e\u0438\u0437\u0432\u043e\u0434\u0441\u0442\u0432\u0435\u043d\u043d\u0430\u044f \u043f\u0440\u0430\u043a\u0442\u0438\u043a\u0430/\u041f\u0440\u043e\u0435\u043a\u0442/dataset/images/Rostselmash-1/whole/images/240521_gopro9_gx020424_00483.jpg",
      "prediction_type": "ObjectDetectionModel"
    },
    {
      "x": 390.0,
      "y": 616.0,
      "width": 36.0,
      "height": 28.0,
      "confidence": 0.628935694694519,
      "class": "plants",
      "class_id": 0,
      "detection_id": "a1bda476-9d6e-4ff7-bfbe-d62c30abde2f",
      "image_path": "C:/Own/University/\u0414\u0413\u0422\u0423/\u0412\u041c\u041e/6 \u0441\u0435\u043c\u0435\u0441\u0442\u0440/\u041f\u0440\u043e\u0438\u0437\u0432\u043e\u0434\u0441\u0442\u0432\u0435\u043d\u043d\u0430\u044f \u043f\u0440\u0430\u043a\u0442\u0438\u043a\u0430/\u041f\u0440\u043e\u0435\u043a\u0442/dataset/images/Rostselmash-1/whole/images/240521_gopro9_gx020424_00483.jpg",
      "prediction_type": "ObjectDetectionModel"
    },
    {
      "x": 128.5,
      "y": 251.0,
      "width": 37.0,
      "height": 16.0,
      "confidence": 0.6281068325042725,
      "class": "plants",
      "class_id": 0,
      "detection_id": "3b62ab4c-800d-4e36-ba0b-fd6c30329186",
      "image_path": "C:/Own/University/\u0414\u0413\u0422\u0423/\u0412\u041c\u041e/6 \u0441\u0435\u043c\u0435\u0441\u0442\u0440/\u041f\u0440\u043e\u0438\u0437\u0432\u043e\u0434\u0441\u0442\u0432\u0435\u043d\u043d\u0430\u044f \u043f\u0440\u0430\u043a\u0442\u0438\u043a\u0430/\u041f\u0440\u043e\u0435\u043a\u0442/dataset/images/Rostselmash-1/whole/images/240521_gopro9_gx020424_00483.jpg",
      "prediction_type": "ObjectDetectionModel"
    },
    {
      "x": 569.5,
      "y": 551.5,
      "width": 29.0,
      "height": 21.0,
      "confidence": 0.6278964281082153,
      "class": "plants",
      "class_id": 0,
      "detection_id": "fdb564ce-d241-4b23-8913-4537ef24b761",
      "image_path": "C:/Own/University/\u0414\u0413\u0422\u0423/\u0412\u041c\u041e/6 \u0441\u0435\u043c\u0435\u0441\u0442\u0440/\u041f\u0440\u043e\u0438\u0437\u0432\u043e\u0434\u0441\u0442\u0432\u0435\u043d\u043d\u0430\u044f \u043f\u0440\u0430\u043a\u0442\u0438\u043a\u0430/\u041f\u0440\u043e\u0435\u043a\u0442/dataset/images/Rostselmash-1/whole/images/240521_gopro9_gx020424_00483.jpg",
      "prediction_type": "ObjectDetectionModel"
    },
    {
      "x": 559.0,
      "y": 467.0,
      "width": 30.0,
      "height": 18.0,
      "confidence": 0.610277533531189,
      "class": "plants",
      "class_id": 0,
      "detection_id": "049c5f18-57bb-42b1-9f71-c3c858eb272a",
      "image_path": "C:/Own/University/\u0414\u0413\u0422\u0423/\u0412\u041c\u041e/6 \u0441\u0435\u043c\u0435\u0441\u0442\u0440/\u041f\u0440\u043e\u0438\u0437\u0432\u043e\u0434\u0441\u0442\u0432\u0435\u043d\u043d\u0430\u044f \u043f\u0440\u0430\u043a\u0442\u0438\u043a\u0430/\u041f\u0440\u043e\u0435\u043a\u0442/dataset/images/Rostselmash-1/whole/images/240521_gopro9_gx020424_00483.jpg",
      "prediction_type": "ObjectDetectionModel"
    },
    {
      "x": 597.5,
      "y": 449.5,
      "width": 51.0,
      "height": 23.0,
      "confidence": 0.6018163561820984,
      "class": "plants",
      "class_id": 0,
      "detection_id": "80b9843e-73b3-495d-963f-4d5fe687aa9b",
      "image_path": "C:/Own/University/\u0414\u0413\u0422\u0423/\u0412\u041c\u041e/6 \u0441\u0435\u043c\u0435\u0441\u0442\u0440/\u041f\u0440\u043e\u0438\u0437\u0432\u043e\u0434\u0441\u0442\u0432\u0435\u043d\u043d\u0430\u044f \u043f\u0440\u0430\u043a\u0442\u0438\u043a\u0430/\u041f\u0440\u043e\u0435\u043a\u0442/dataset/images/Rostselmash-1/whole/images/240521_gopro9_gx020424_00483.jpg",
      "prediction_type": "ObjectDetectionModel"
    },
    {
      "x": 332.0,
      "y": 332.0,
      "width": 60.0,
      "height": 28.0,
      "confidence": 0.5970830917358398,
      "class": "plants",
      "class_id": 0,
      "detection_id": "a4178033-6f14-41f7-aded-867974695f35",
      "image_path": "C:/Own/University/\u0414\u0413\u0422\u0423/\u0412\u041c\u041e/6 \u0441\u0435\u043c\u0435\u0441\u0442\u0440/\u041f\u0440\u043e\u0438\u0437\u0432\u043e\u0434\u0441\u0442\u0432\u0435\u043d\u043d\u0430\u044f \u043f\u0440\u0430\u043a\u0442\u0438\u043a\u0430/\u041f\u0440\u043e\u0435\u043a\u0442/dataset/images/Rostselmash-1/whole/images/240521_gopro9_gx020424_00483.jpg",
      "prediction_type": "ObjectDetectionModel"
    },
    {
      "x": 418.5,
      "y": 603.5,
      "width": 29.0,
      "height": 21.0,
      "confidence": 0.5959576368331909,
      "class": "plants",
      "class_id": 0,
      "detection_id": "b2e0ef5e-f6b5-4fb2-ad38-24612db1e47a",
      "image_path": "C:/Own/University/\u0414\u0413\u0422\u0423/\u0412\u041c\u041e/6 \u0441\u0435\u043c\u0435\u0441\u0442\u0440/\u041f\u0440\u043e\u0438\u0437\u0432\u043e\u0434\u0441\u0442\u0432\u0435\u043d\u043d\u0430\u044f \u043f\u0440\u0430\u043a\u0442\u0438\u043a\u0430/\u041f\u0440\u043e\u0435\u043a\u0442/dataset/images/Rostselmash-1/whole/images/240521_gopro9_gx020424_00483.jpg",
      "prediction_type": "ObjectDetectionModel"
    },
    {
      "x": 176.0,
      "y": 65.5,
      "width": 38.0,
      "height": 25.0,
      "confidence": 0.5956623554229736,
      "class": "plants",
      "class_id": 0,
      "detection_id": "fe964b96-fd25-4998-bb69-567f952b0495",
      "image_path": "C:/Own/University/\u0414\u0413\u0422\u0423/\u0412\u041c\u041e/6 \u0441\u0435\u043c\u0435\u0441\u0442\u0440/\u041f\u0440\u043e\u0438\u0437\u0432\u043e\u0434\u0441\u0442\u0432\u0435\u043d\u043d\u0430\u044f \u043f\u0440\u0430\u043a\u0442\u0438\u043a\u0430/\u041f\u0440\u043e\u0435\u043a\u0442/dataset/images/Rostselmash-1/whole/images/240521_gopro9_gx020424_00483.jpg",
      "prediction_type": "ObjectDetectionModel"
    },
    {
      "x": 263.0,
      "y": 59.5,
      "width": 62.0,
      "height": 33.0,
      "confidence": 0.5845670700073242,
      "class": "plants",
      "class_id": 0,
      "detection_id": "129a944b-a339-4548-ba66-ef1c3a8644c9",
      "image_path": "C:/Own/University/\u0414\u0413\u0422\u0423/\u0412\u041c\u041e/6 \u0441\u0435\u043c\u0435\u0441\u0442\u0440/\u041f\u0440\u043e\u0438\u0437\u0432\u043e\u0434\u0441\u0442\u0432\u0435\u043d\u043d\u0430\u044f \u043f\u0440\u0430\u043a\u0442\u0438\u043a\u0430/\u041f\u0440\u043e\u0435\u043a\u0442/dataset/images/Rostselmash-1/whole/images/240521_gopro9_gx020424_00483.jpg",
      "prediction_type": "ObjectDetectionModel"
    },
    {
      "x": 239.5,
      "y": 182.5,
      "width": 71.0,
      "height": 35.0,
      "confidence": 0.5799432992935181,
      "class": "plants",
      "class_id": 0,
      "detection_id": "52738c39-6a75-45f6-b5cd-ffec599451a4",
      "image_path": "C:/Own/University/\u0414\u0413\u0422\u0423/\u0412\u041c\u041e/6 \u0441\u0435\u043c\u0435\u0441\u0442\u0440/\u041f\u0440\u043e\u0438\u0437\u0432\u043e\u0434\u0441\u0442\u0432\u0435\u043d\u043d\u0430\u044f \u043f\u0440\u0430\u043a\u0442\u0438\u043a\u0430/\u041f\u0440\u043e\u0435\u043a\u0442/dataset/images/Rostselmash-1/whole/images/240521_gopro9_gx020424_00483.jpg",
      "prediction_type": "ObjectDetectionModel"
    },
    {
      "x": 241.0,
      "y": 263.0,
      "width": 22.0,
      "height": 12.0,
      "confidence": 0.5722970366477966,
      "class": "plants",
      "class_id": 0,
      "detection_id": "bc856eb3-db48-4a66-9e14-b5c1182474c2",
      "image_path": "C:/Own/University/\u0414\u0413\u0422\u0423/\u0412\u041c\u041e/6 \u0441\u0435\u043c\u0435\u0441\u0442\u0440/\u041f\u0440\u043e\u0438\u0437\u0432\u043e\u0434\u0441\u0442\u0432\u0435\u043d\u043d\u0430\u044f \u043f\u0440\u0430\u043a\u0442\u0438\u043a\u0430/\u041f\u0440\u043e\u0435\u043a\u0442/dataset/images/Rostselmash-1/whole/images/240521_gopro9_gx020424_00483.jpg",
      "prediction_type": "ObjectDetectionModel"
    },
    {
      "x": 456.0,
      "y": 191.5,
      "width": 36.0,
      "height": 23.0,
      "confidence": 0.5664348602294922,
      "class": "plants",
      "class_id": 0,
      "detection_id": "3bb6b4a3-83fb-4e2d-9593-761bb401af14",
      "image_path": "C:/Own/University/\u0414\u0413\u0422\u0423/\u0412\u041c\u041e/6 \u0441\u0435\u043c\u0435\u0441\u0442\u0440/\u041f\u0440\u043e\u0438\u0437\u0432\u043e\u0434\u0441\u0442\u0432\u0435\u043d\u043d\u0430\u044f \u043f\u0440\u0430\u043a\u0442\u0438\u043a\u0430/\u041f\u0440\u043e\u0435\u043a\u0442/dataset/images/Rostselmash-1/whole/images/240521_gopro9_gx020424_00483.jpg",
      "prediction_type": "ObjectDetectionModel"
    },
    {
      "x": 484.0,
      "y": 6.0,
      "width": 34.0,
      "height": 12.0,
      "confidence": 0.5648595690727234,
      "class": "plants",
      "class_id": 0,
      "detection_id": "f1b6808e-02eb-4962-9aed-2f9bdbc076d8",
      "image_path": "C:/Own/University/\u0414\u0413\u0422\u0423/\u0412\u041c\u041e/6 \u0441\u0435\u043c\u0435\u0441\u0442\u0440/\u041f\u0440\u043e\u0438\u0437\u0432\u043e\u0434\u0441\u0442\u0432\u0435\u043d\u043d\u0430\u044f \u043f\u0440\u0430\u043a\u0442\u0438\u043a\u0430/\u041f\u0440\u043e\u0435\u043a\u0442/dataset/images/Rostselmash-1/whole/images/240521_gopro9_gx020424_00483.jpg",
      "prediction_type": "ObjectDetectionModel"
    },
    {
      "x": 62.0,
      "y": 347.0,
      "width": 52.0,
      "height": 30.0,
      "confidence": 0.5576688051223755,
      "class": "plants",
      "class_id": 0,
      "detection_id": "f8c4f1ab-c2f6-4980-8861-ae182ee028cf",
      "image_path": "C:/Own/University/\u0414\u0413\u0422\u0423/\u0412\u041c\u041e/6 \u0441\u0435\u043c\u0435\u0441\u0442\u0440/\u041f\u0440\u043e\u0438\u0437\u0432\u043e\u0434\u0441\u0442\u0432\u0435\u043d\u043d\u0430\u044f \u043f\u0440\u0430\u043a\u0442\u0438\u043a\u0430/\u041f\u0440\u043e\u0435\u043a\u0442/dataset/images/Rostselmash-1/whole/images/240521_gopro9_gx020424_00483.jpg",
      "prediction_type": "ObjectDetectionModel"
    },
    {
      "x": 67.5,
      "y": 37.0,
      "width": 21.0,
      "height": 14.0,
      "confidence": 0.5563496351242065,
      "class": "plants",
      "class_id": 0,
      "detection_id": "5009b86c-c520-49e9-8204-103560e8c8c2",
      "image_path": "C:/Own/University/\u0414\u0413\u0422\u0423/\u0412\u041c\u041e/6 \u0441\u0435\u043c\u0435\u0441\u0442\u0440/\u041f\u0440\u043e\u0438\u0437\u0432\u043e\u0434\u0441\u0442\u0432\u0435\u043d\u043d\u0430\u044f \u043f\u0440\u0430\u043a\u0442\u0438\u043a\u0430/\u041f\u0440\u043e\u0435\u043a\u0442/dataset/images/Rostselmash-1/whole/images/240521_gopro9_gx020424_00483.jpg",
      "prediction_type": "ObjectDetectionModel"
    },
    {
      "x": 490.5,
      "y": 584.5,
      "width": 39.0,
      "height": 29.0,
      "confidence": 0.5452535152435303,
      "class": "plants",
      "class_id": 0,
      "detection_id": "a5f9e095-28de-4dac-8cf9-1bdbe456bced",
      "image_path": "C:/Own/University/\u0414\u0413\u0422\u0423/\u0412\u041c\u041e/6 \u0441\u0435\u043c\u0435\u0441\u0442\u0440/\u041f\u0440\u043e\u0438\u0437\u0432\u043e\u0434\u0441\u0442\u0432\u0435\u043d\u043d\u0430\u044f \u043f\u0440\u0430\u043a\u0442\u0438\u043a\u0430/\u041f\u0440\u043e\u0435\u043a\u0442/dataset/images/Rostselmash-1/whole/images/240521_gopro9_gx020424_00483.jpg",
      "prediction_type": "ObjectDetectionModel"
    },
    {
      "x": 167.5,
      "y": 111.5,
      "width": 27.0,
      "height": 15.0,
      "confidence": 0.5389028191566467,
      "class": "plants",
      "class_id": 0,
      "detection_id": "879522b3-2174-4fe1-ab06-4dee5890a24e",
      "image_path": "C:/Own/University/\u0414\u0413\u0422\u0423/\u0412\u041c\u041e/6 \u0441\u0435\u043c\u0435\u0441\u0442\u0440/\u041f\u0440\u043e\u0438\u0437\u0432\u043e\u0434\u0441\u0442\u0432\u0435\u043d\u043d\u0430\u044f \u043f\u0440\u0430\u043a\u0442\u0438\u043a\u0430/\u041f\u0440\u043e\u0435\u043a\u0442/dataset/images/Rostselmash-1/whole/images/240521_gopro9_gx020424_00483.jpg",
      "prediction_type": "ObjectDetectionModel"
    },
    {
      "x": 388.5,
      "y": 500.0,
      "width": 21.0,
      "height": 14.0,
      "confidence": 0.5329912900924683,
      "class": "plants",
      "class_id": 0,
      "detection_id": "464be9a1-e26e-449c-9ef9-a5b49242f1f7",
      "image_path": "C:/Own/University/\u0414\u0413\u0422\u0423/\u0412\u041c\u041e/6 \u0441\u0435\u043c\u0435\u0441\u0442\u0440/\u041f\u0440\u043e\u0438\u0437\u0432\u043e\u0434\u0441\u0442\u0432\u0435\u043d\u043d\u0430\u044f \u043f\u0440\u0430\u043a\u0442\u0438\u043a\u0430/\u041f\u0440\u043e\u0435\u043a\u0442/dataset/images/Rostselmash-1/whole/images/240521_gopro9_gx020424_00483.jpg",
      "prediction_type": "ObjectDetectionModel"
    },
    {
      "x": 138.0,
      "y": 217.0,
      "width": 24.0,
      "height": 14.0,
      "confidence": 0.5327228307723999,
      "class": "plants",
      "class_id": 0,
      "detection_id": "97fff35a-2096-4a38-8804-e6ec50b99712",
      "image_path": "C:/Own/University/\u0414\u0413\u0422\u0423/\u0412\u041c\u041e/6 \u0441\u0435\u043c\u0435\u0441\u0442\u0440/\u041f\u0440\u043e\u0438\u0437\u0432\u043e\u0434\u0441\u0442\u0432\u0435\u043d\u043d\u0430\u044f \u043f\u0440\u0430\u043a\u0442\u0438\u043a\u0430/\u041f\u0440\u043e\u0435\u043a\u0442/dataset/images/Rostselmash-1/whole/images/240521_gopro9_gx020424_00483.jpg",
      "prediction_type": "ObjectDetectionModel"
    },
    {
      "x": 357.0,
      "y": 618.0,
      "width": 38.0,
      "height": 30.0,
      "confidence": 0.5303150415420532,
      "class": "plants",
      "class_id": 0,
      "detection_id": "da5df5ac-a6f9-4741-8736-bc9b3289b09d",
      "image_path": "C:/Own/University/\u0414\u0413\u0422\u0423/\u0412\u041c\u041e/6 \u0441\u0435\u043c\u0435\u0441\u0442\u0440/\u041f\u0440\u043e\u0438\u0437\u0432\u043e\u0434\u0441\u0442\u0432\u0435\u043d\u043d\u0430\u044f \u043f\u0440\u0430\u043a\u0442\u0438\u043a\u0430/\u041f\u0440\u043e\u0435\u043a\u0442/dataset/images/Rostselmash-1/whole/images/240521_gopro9_gx020424_00483.jpg",
      "prediction_type": "ObjectDetectionModel"
    },
    {
      "x": 354.0,
      "y": 189.0,
      "width": 44.0,
      "height": 24.0,
      "confidence": 0.5199556946754456,
      "class": "plants",
      "class_id": 0,
      "detection_id": "09a27eac-232e-4d59-80d5-1c892274a878",
      "image_path": "C:/Own/University/\u0414\u0413\u0422\u0423/\u0412\u041c\u041e/6 \u0441\u0435\u043c\u0435\u0441\u0442\u0440/\u041f\u0440\u043e\u0438\u0437\u0432\u043e\u0434\u0441\u0442\u0432\u0435\u043d\u043d\u0430\u044f \u043f\u0440\u0430\u043a\u0442\u0438\u043a\u0430/\u041f\u0440\u043e\u0435\u043a\u0442/dataset/images/Rostselmash-1/whole/images/240521_gopro9_gx020424_00483.jpg",
      "prediction_type": "ObjectDetectionModel"
    },
    {
      "x": 491.0,
      "y": 477.5,
      "width": 24.0,
      "height": 15.0,
      "confidence": 0.5140235424041748,
      "class": "plants",
      "class_id": 0,
      "detection_id": "5b1d0741-c9f4-47e6-b0eb-c7b00f02a8f8",
      "image_path": "C:/Own/University/\u0414\u0413\u0422\u0423/\u0412\u041c\u041e/6 \u0441\u0435\u043c\u0435\u0441\u0442\u0440/\u041f\u0440\u043e\u0438\u0437\u0432\u043e\u0434\u0441\u0442\u0432\u0435\u043d\u043d\u0430\u044f \u043f\u0440\u0430\u043a\u0442\u0438\u043a\u0430/\u041f\u0440\u043e\u0435\u043a\u0442/dataset/images/Rostselmash-1/whole/images/240521_gopro9_gx020424_00483.jpg",
      "prediction_type": "ObjectDetectionModel"
    },
    {
      "x": 309.5,
      "y": 627.5,
      "width": 53.0,
      "height": 23.0,
      "confidence": 0.5024663209915161,
      "class": "plants",
      "class_id": 0,
      "detection_id": "6001ba81-b99f-4c16-ab1a-b7440de31ca8",
      "image_path": "C:/Own/University/\u0414\u0413\u0422\u0423/\u0412\u041c\u041e/6 \u0441\u0435\u043c\u0435\u0441\u0442\u0440/\u041f\u0440\u043e\u0438\u0437\u0432\u043e\u0434\u0441\u0442\u0432\u0435\u043d\u043d\u0430\u044f \u043f\u0440\u0430\u043a\u0442\u0438\u043a\u0430/\u041f\u0440\u043e\u0435\u043a\u0442/dataset/images/Rostselmash-1/whole/images/240521_gopro9_gx020424_00483.jpg",
      "prediction_type": "ObjectDetectionModel"
    }
  ],
  "image": {
    "width": "640",
    "height": "640"
  }
}